D flip-flop/dff.v
module dff (
    input clk,
    input D,
    output reg Q
);
    always @(posedge clk) begin
        Q <= D;
    end
endmodule

D flip-flop/dff_tb.v
`timescale 1ns/1ps

module dff_tb;
reg clk;
reg D;
wire Q;
dff uut(
    .clk(clk),
    .D(D),
    .Q(Q)
);
always #5 clk = ~clk;
initial begin

    $dumpfile("dff.vcd");
    $dumpvars(0,dff_tb);

    clk = 0;

    D = 0;
    #10;

    D = 1;
    #10;

    D = 0;
    #10;

    D = 1;
    #10;

    $finish;
    
end
    
endmodule

D flip-flop/dff.vcd
$date
	Thu Jun 11 07:53:56 2026
$end
$version
	Icarus Verilog
$end
$timescale
	1ps
$end
$scope module dff_tb $end
$var wire 1 ! Q $end
$var reg 1 " D $end
$var reg 1 # clk $end
$scope module uut $end
$var wire 1 " D $end
$var wire 1 # clk $end
$var reg 1 ! Q $end
$upscope $end
$upscope $end
$enddefinitions $end
$comment Show the parameter values. $end
$dumpall
$end
#0
$dumpvars
0#
0"
x!
$end
#5000
0!
1#
#10000
0#
1"
#15000
1!
1#
#20000
0#
0"
#25000
0!
1#
#30000
0#
1"
#35000
1!
1#
