Create an 8-bit register/reg8.v
module reg8 (
    input clk,
    input [7:0] D,
    output reg [7:0] Q
);
    always @(posedge clk) begin
        Q = D;
    end
endmodule

Create an 8-bit register/reg8_tb.v
`timescale 1ns / 1ps

module reg8_tb;
reg clk;
reg [7:0] D;
wire [7:0] Q;
reg8 uut(
    .clk(clk),
    .D(D),
    .Q(Q)
);
always #5 clk = ~clk;
initial begin

    $dumpfile("reg8.vcd");
    $dumpvars(0,reg8_tb);

    clk = 0;

    D = 8'b00000000;
    #10;

    D = 8'b11111111;
    #10;

    D = 8'b10101010;
    #10;

    D = 8'b01010101;
    #10;

    $finish;
    
end

endmodule

Create an 8-bit register/reg8.vcd
$date
	Thu Jun 11 07:45:33 2026
$end
$version
	Icarus Verilog
$end
$timescale
	1ps
$end
$scope module reg8_tb $end
$var wire 8 ! Q [7:0] $end
$var reg 8 " D [7:0] $end
$var reg 1 # clk $end
$scope module uut $end
$var wire 8 $ D [7:0] $end
$var wire 1 # clk $end
$var reg 8 % Q [7:0] $end
$upscope $end
$upscope $end
$enddefinitions $end
$comment Show the parameter values. $end
$dumpall
$end
#0
$dumpvars
bx %
b0 $
0#
b0 "
bx !
$end
#5000
b0 !
b0 %
1#
#10000
0#
b11111111 "
b11111111 $
#15000
b11111111 !
b11111111 %
1#
#20000
0#
b10101010 "
b10101010 $
#25000
b10101010 !
b10101010 %
1#
#30000
0#
b1010101 "
b1010101 $
#35000
b1010101 !
b1010101 %
1#
