nptl/example1.v
module example1 (
    input A,B,C,D,E,F,
    output Y
);

wire t1,t2,t3;

nand #1 G1(t1,A,B);
and #2 G2(t2,C,~B,D);
nor #1 G3(t3,E,F);
nand #1 G4(Y,t1,t2,t3);

endmodule

nptl/example1_tb.v
module testbench;
    reg A,B,C,D,E,F;
    wire Y;
    example1 DUT (
        A,
        B,
        C,
        D,
        E,
        F,
        Y
    );
    initial begin
        $dumpfile("example1.vcd");
        $dumpvars(0,testbench);

        A = 0; B = 0; C = 0; D = 1; E = 0; F = 0;;
        #10;

        A = 1; B = 0; C = 1; D = 1; E = 0; F = 0;
        #10;

        A = 1;C = 0;
        #10;

        F = 1;
        #10;

        $finish;
    end
endmodule

nptl/example1.vcd
$date
	Tue Jun 16 10:43:45 2026
$end
$version
	Icarus Verilog
$end
$timescale
	1s
$end
$scope module testbench $end
$var wire 1 ! Y $end
$var reg 1 " A $end
$var reg 1 # B $end
$var reg 1 $ C $end
$var reg 1 % D $end
$var reg 1 & E $end
$var reg 1 ' F $end
$scope module DUT $end
$var wire 1 " A $end
$var wire 1 # B $end
$var wire 1 $ C $end
$var wire 1 % D $end
$var wire 1 & E $end
$var wire 1 ' F $end
$var wire 1 ! Y $end
$var wire 1 ( t1 $end
$var wire 1 ) t2 $end
$var wire 1 * t3 $end
$upscope $end
$upscope $end
$enddefinitions $end
$comment Show the parameter values. $end
$dumpall
$end
#0
$dumpvars
x*
x)
x(
0'
0&
1%
0$
0#
0"
x!
$end
#1
1*
1(
#2
0)
#3
1!
#10
1$
1"
#12
1)
#13
0!
#20
0$
#22
0)
#23
1!
#30
1'
#31
0*
